gillespie/__init__.py
gillespie/_gillespie.py
gillespie-0.0.3.dist-info/LICENSE
gillespie-0.0.3.dist-info/METADATA
gillespie-0.0.3.dist-info/WHEEL
gillespie-0.0.3.dist-info/top_level.txt
gillespie-0.0.3.dist-info/RECORD
