Metadata-Version: 2.1
Name: gillespie
Version: 0.0.3
Summary: Pure Python implementation of the Gillespie algorithm for stochastic simulations.
Home-page: https://github.com/sueskind/gillespie
Author: sueskind
Author-email: 52210599+sueskind@users.noreply.github.com
License: UNKNOWN
Platform: UNKNOWN
Classifier: Programming Language :: Python :: 3
Classifier: Programming Language :: Python :: 3.6
Classifier: Programming Language :: Python :: 3.7
Classifier: Programming Language :: Python :: 3.8
Classifier: Programming Language :: Python :: 3.9
Classifier: Programming Language :: Python :: 3.10
Classifier: Programming Language :: Python :: 3.11
Classifier: License :: OSI Approved :: MIT License
Classifier: Operating System :: OS Independent
License-File: LICENSE
